tclab/__init__.py
tclab/lab.py
tclab_sdk-2.5.5.dist-info/METADATA
tclab_sdk-2.5.5.dist-info/WHEEL
tclab_sdk-2.5.5.dist-info/entry_points.txt
tclab_sdk-2.5.5.dist-info/top_level.txt
tclab_sdk-2.5.5.dist-info/RECORD
