Metadata-Version: 2.1
Name: tclab-sdk
Version: 2.5.5
Summary: TC Laboratory Central_Management_System Client Module
Home-page: UNKNOWN
Author: Haotian Yang
Author-email: yht1592754117@126.com
License: UNKNOWN
Platform: UNKNOWN
Classifier: Programming Language :: Python :: 3
Classifier: License :: OSI Approved :: MIT License
Classifier: Operating System :: OS Independent
Requires-Python: >=3
Requires-Dist: requests
Requires-Dist: pycryptodome
Requires-Dist: psutil
Requires-Dist: rich
Requires-Dist: blessed
